dependix_core/__init__.py
dependix_core/bean_definition.py
dependix_core/config.py
dependix_core/container.py
dependix_core/decorators.py
dependix_core/exceptions.py
dependix_core/tests/__init__.py
dependix_core/tests/test_container.py
dependix_core-0.1.0.dist-info/licenses/LICENSE
dependix_core-0.1.0.dist-info/METADATA
dependix_core-0.1.0.dist-info/WHEEL
dependix_core-0.1.0.dist-info/top_level.txt
dependix_core-0.1.0.dist-info/RECORD
