Metadata-Version: 2.4
Name: dependix_core
Version: 0.1.0
Summary: Dependix Core, new python coding framework.
Author-email: Grégoire Meunier <gregoire.meunie@live.fr>
Classifier: Programming Language :: Python :: 3
Classifier: License :: OSI Approved :: MIT License
Classifier: Operating System :: OS Independent
Requires-Python: >=3.8
License-File: LICENSE
Requires-Dist: pyyaml
Requires-Dist: black
Requires-Dist: pytest
Requires-Dist: coverage
Requires-Dist: pytest-cov
Requires-Dist: pylint
Dynamic: license-file
